hephaestus_setup_mcp/__init__.py
hephaestus_setup_mcp-0.1.0.dist-info/METADATA
hephaestus_setup_mcp-0.1.0.dist-info/WHEEL
hephaestus_setup_mcp-0.1.0.dist-info/entry_points.txt
hephaestus_setup_mcp-0.1.0.dist-info/licenses/LICENSE
hephaestus_setup_mcp-0.1.0.dist-info/RECORD
