Metadata-Version: 2.4
Name: hephaestus-setup-mcp
Version: 0.1.0
Summary: MCP server for setting up and managing Hephaestus Docker environment
Project-URL: Homepage, https://github.com/alehayeb/hephaestus-docker-power
Project-URL: Repository, https://github.com/alehayeb/hephaestus-docker-power
Author: Hephaestus Community
License-Expression: MIT
License-File: LICENSE
Keywords: docker,hephaestus,mcp,qdrant,setup
Classifier: Development Status :: 3 - Alpha
Classifier: Intended Audience :: Developers
Classifier: License :: OSI Approved :: MIT License
Classifier: Programming Language :: Python :: 3
Classifier: Programming Language :: Python :: 3.10
Classifier: Programming Language :: Python :: 3.11
Classifier: Programming Language :: Python :: 3.12
Requires-Python: >=3.10
Requires-Dist: fastmcp>=0.1.0
Requires-Dist: pyyaml>=6.0
